COPYING
MANIFEST.in
setup.py
django_dynamic_subdomains.egg-info/PKG-INFO
django_dynamic_subdomains.egg-info/SOURCES.txt
django_dynamic_subdomains.egg-info/dependency_links.txt
django_dynamic_subdomains.egg-info/requires.txt
django_dynamic_subdomains.egg-info/top_level.txt
dynamic_subdomains/__init__.py
dynamic_subdomains/app_settings.py
dynamic_subdomains/apps.py
dynamic_subdomains/http.py
dynamic_subdomains/middleware.py
dynamic_subdomains/reverse.py
dynamic_subdomains/subdomains.py
dynamic_subdomains/urls.py
dynamic_subdomains/utils.py
dynamic_subdomains/views.py
dynamic_subdomains/templatetags/__init__.py
dynamic_subdomains/templatetags/dynamic_subdomains.py