Metadata-Version: 1.0
Name: django-dynamic-subdomains
Version: 1.2.0
Summary: Dynamic and static subdomain support for Django.
Home-page: https://chris-lamb.co.uk/projects/django-dynamic-subdomains/
Author: Chris Lamb
Author-email: chris@chris-lamb.co.uk
License: BSD
Platform: UNKNOWN
